tps_rck_sdk/__init__.py
tps_rck_sdk/api.py
tps_rck_sdk/config.py
tps_rck_sdk/exceptions.py
tps_rck_sdk/model.py
tps_rck_sdk/rck_client.py
tps_rck_sdk-0.1.1.dist-info/METADATA
tps_rck_sdk-0.1.1.dist-info/WHEEL
tps_rck_sdk-0.1.1.dist-info/top_level.txt
tps_rck_sdk-0.1.1.dist-info/RECORD
