Metadata-Version: 2.4
Name: tps-rck-sdk
Version: 0.1.1
Summary: Official Python SDK for the Relational Calculate Kernel (RCK)
Author-email: Topos-Pathless-Service <omorsablin@gmail.com>
Project-URL: Homepage, https://github.com/TPS/rck-sdk
Project-URL: Issues, https://github.com/TPS/rck-sdk/issues
Classifier: Programming Language :: Python :: 3
Classifier: Operating System :: OS Independent
Classifier: Intended Audience :: Developers
Classifier: Topic :: Software Development :: Libraries :: Python Modules
Requires-Python: >=3.8
Requires-Dist: requests>=2.28.0
Requires-Dist: pydantic>=2.0
Requires-Dist: ratelimit>=2.2.1
